apidownload/__init__.py
apidownload/__main__.py
apidownload/apidownload.json
apidownload/default_settings.json
apidownload-2.1.1.dist-info/LICENSE.txt
apidownload-2.1.1.dist-info/METADATA
apidownload-2.1.1.dist-info/WHEEL
apidownload-2.1.1.dist-info/entry_points.txt
apidownload-2.1.1.dist-info/top_level.txt
apidownload-2.1.1.dist-info/RECORD
