Metadata-Version: 2.1
Name: apidownload
Version: 2.1.1
Summary: Download the data from an API endpoint to a file
Author: Joe Greaves
Project-URL: Homepage, https://github.com/Grvs44/API-Download
Classifier: Programming Language :: Python :: 3
Classifier: License :: OSI Approved :: BSD License
Classifier: Operating System :: OS Independent
Requires-Python: >=3.10
License-File: LICENSE.txt
Requires-Dist: requests (==2.31.0)
